{
  "Version": 3,
  "Meta": {
    "Duration": 13.333,
    "Fps": 30.0,
    "Loop": true,
    "AreBeziersRestricted": true,
    "FadeInTime": 0.0,
    "FadeOutTime": 0.0,
    "CurveCount": 198,
    "TotalSegmentCount": 693,
    "TotalPointCount": 827,
    "UserDataCount": 2,
    "TotalUserDataSize": 0
  },
  "Curves": [
    {
      "Target": "Parameter",
      "Id": "Param_EFFECT_SIZE",
      "FadeInTime": -1.0,
      "FadeOutTime": -1.0,
      "Segments": [
        0,
        0,
        0,
        1.2,
        -6,
        0,
        1.5,
        6,
        0,
        2,
        -12,
        0,
        6.667,
        0,
        2,
        13.333,
        0
      ]
    },
    {
      "Target": "Parameter",
      "Id": "Param_EFFECT_ROT",
      "FadeInTime": -1.0,
      "FadeOutTime": -1.0,
      "Segments": [
        0,
        0,
        1,
        0.378,
        -0.667,
        0.755,
        -1.333,
        1.133,
        -2,
        1,
        1.233,
        0,
        1.333,
        2,
        1.433,
        4,
        1,
        1.544,
        2,
        1.656,
        0,
        1.767,
        -2,
        1,
        1.867,
        -0.333,
        1.967,
        1.333,
        2.067,
        3,
        1,
        2.156,
        1.333,
        2.244,
        -0.333,
        2.333,
        -2,
        1,
        3.778,
        -1.333,
        5.222,
        -0.667,
        6.667,
        0,
        2,
        13.333,
        0
      ]
    },
    {
      "Target": "Parameter",
      "Id": "Param_EFFECT_MOVE_X",
      "FadeInTime": -1.0,
      "FadeOutTime": -1.0,
      "Segments": [
        0,
        -2.12,
        2,
        1.7,
        -2.12,
        0,
        6.667,
        0,
        2,
        13.333,
        0
      ]
    },
    {
      "Target": "Parameter",
      "Id": "Parameffectq",
      "FadeInTime": -1.0,
      "FadeOutTime": -1.0,
      "Segments": [
        0,
        0,
        2,
        1.2,
        0,
        0,
        1.5,
        30,
        2,
        1.867,
        30,
        0,
        2.367,
        0,
        2,
        6.667,
        0,
        2,
        13.333,
        0
      ]
    },
    {
      "Target": "Parameter",
      "Id": "ParamZSBDXZ",
      "FadeInTime": -1.0,
      "FadeOutTime": -1.0,
      "Segments": [
        0,
        0,
        1,
        0.1,
        -0.441,
        0.2,
        -10.173,
        0.3,
        -10.173,
        0,
        0.8,
        15.584,
        0,
        2.133,
        -4.92,
        0,
        2.267,
        -4.8,
        2,
        4.033,
        -4.8,
        0,
        4.733,
        11,
        2,
        6.667,
        11,
        0,
        7.233,
        -13.92,
        0,
        8.2,
        0,
        0,
        9.467,
        -4.8,
        2,
        9.867,
        -4.8,
        0,
        10.367,
        -8.458,
        0,
        11.367,
        6,
        0,
        12.567,
        0,
        2,
        13.133,
        0,
        2,
        13.333,
        0
      ]
    },
    {
      "Target": "Parameter",
      "Id": "ParamZSBDSS",
      "FadeInTime": -1.0,
      "FadeOutTime": -1.0,
      "Segments": [
        0,
        0,
        0,
        2.267,
        -30,
        0,
        4.033,
        -10.17,
        0,
        4.467,
        -18,
        0,
        4.9,
        30,
        0,
        5.967,
        2,
        0,
        6.667,
        27.29,
        1,
        6.867,
        27.29,
        7.067,
        1.656,
        7.267,
        0,
        1,
        8,
        -6.07,
        8.734,
        -7.44,
        9.467,
        -7.44,
        2,
        9.867,
        -7.44,
        0,
        13.133,
        0,
        2,
        13.333,
        0
      ]
    },
    {
      "Target": "Parameter",
      "Id": "ParamZSQBXZ",
      "FadeInTime": -1.0,
      "FadeOutTime": -1.0,
      "Segments": [
        0,
        0,
        2,
        0.167,
        0,
        1,
        0.411,
        19.665,
        0.656,
        27,
        0.9,
        27,
        1,
        1.111,
        27,
        1.322,
        25.063,
        1.533,
        25,
        1,
        1.778,
        24.927,
        2.022,
        24.94,
        2.267,
        24.94,
        2,
        4.033,
        24.94,
        0,
        4.733,
        0,
        2,
        6.8,
        0,
        0,
        7.6,
        24.96,
        0,
        8.367,
        23,
        1,
        8.734,
        23,
        9.1,
        23.272,
        9.467,
        24.52,
        1,
        9.611,
        25.012,
        9.756,
        26.329,
        9.9,
        26.329,
        0,
        10.533,
        -0.562,
        0,
        11.6,
        1.18,
        0,
        13.133,
        0,
        2,
        13.333,
        0
      ]
    },
    {
      "Target": "Parameter",
      "Id": "ParamZQBQH",
      "FadeInTime": -1.0,
      "FadeOutTime": -1.0,
      "Segments": [
        0,
        0,
        2,
        0.267,
        0,
        0,
        0.667,
        30,
        2,
        2.267,
        30,
        2,
        4.033,
        30,
        0,
        4.733,
        60,
        2,
        6.8,
        60,
        0,
        7.133,
        30,
        2,
        9.467,
        30,
        2,
        9.933,
        30,
        0,
        10.3,
        0,
        2,
        13.133,
        0,
        2,
        13.333,
        0
      ]
    },
    {
      "Target": "Parameter",
      "Id": "ParamZSBQH",
      "FadeInTime": -1.0,
      "FadeOutTime": -1.0,
      "Segments": [
        0,
        0,
        2,
        2.267,
        0,
        2,
        4.033,
        0,
        0,
        4.733,
        30,
        2,
        6.8,
        30,
        0,
        7.133,
        0,
        2,
        9.467,
        0,
        2,
        9.867,
        0,
        2,
        13.133,
        0,
        2,
        13.333,
        0
      ]
    },
    {
      "Target": "Parameter",
      "Id": "Paramzqbqs",
      "FadeInTime": -1.0,
      "FadeOutTime": -1.0,
      "Segments": [
        0,
        0,
        2,
        0.1,
        0,
        0,
        0.433,
        -30,
        0,
        0.767,
        0,
        1,
        1.267,
        0,
        1.767,
        -4.197,
        2.267,
        -7.56,
        1,
        2.856,
        -11.52,
        3.444,
        -12.203,
        4.033,
        -12.203,
        0,
        6.667,
        0,
        2,
        9.933,
        0,
        0,
        10.167,
        -30,
        0,
        10.6,
        0,
        2,
        11.167,
        0,
        2,
        13.133,
        0,
        2,
        13.333,
        0
      ]
    },
    {
      "Target": "Parameter",
      "Id": "ParamYSXZ",
      "FadeInTime": -1.0,
      "FadeOutTime": -1.0,
      "Segments": [
        0,
        0,
        1,
        0.2,
        7.112,
        0.4,
        13,
        0.6,
        13,
        0,
        1.167,
        -30,
        0,
        2.267,
        0,
        2,
        4.033,
        0,
        0,
        6.667,
        4.513,
        1,
        6.8,
        4.513,
        6.934,
        3.204,
        7.067,
        0,
        1,
        7.078,
        -0.267,
        7.089,
        -30,
        7.1,
        -30,
        0,
        7.5,
        18,
        0,
        7.867,
        -29,
        0,
        8.633,
        0,
        2,
        9.467,
        0,
        2,
        9.867,
        0,
        0,
        10.167,
        -8.542,
        0,
        10.633,
        11,
        1,
        11.155,
        11,
        11.678,
        10.278,
        12.2,
        6,
        1,
        12.411,
        4.271,
        12.622,
        -4,
        12.833,
        -4,
        0,
        13.133,
        0,
        2,
        13.333,
        0
      ]
    },
    {
      "Target": "Parameter",
      "Id": "ParamYSYZ",
      "FadeInTime": -1.0,
      "FadeOutTime": -1.0,
      "Segments": [
        0,
        0,
        2,
        2.3,
        0,
        2,
        4.067,
        0,
        1,
        4.145,
        0,
        4.222,
        -1.79,
        4.3,
        -6,
        1,
        4.311,
        -6.601,
        4.322,
        -8.558,
        4.333,
        -9,
        1,
        4.422,
        -12.539,
        4.511,
        -15.964,
        4.6,
        -19,
        1,
        4.656,
        -20.897,
        4.711,
        -23.937,
        4.767,
        -24,
        1,
        5.4,
        -24.722,
        6.034,
        -25,
        6.667,
        -25,
        1,
        6.8,
        -25,
        6.934,
        -22.348,
        7.067,
        -16,
        1,
        7.078,
        -15.471,
        7.089,
        -6.902,
        7.1,
        -6,
        1,
        7.156,
        -1.492,
        7.211,
        0,
        7.267,
        0,
        2,
        9.467,
        0,
        2,
        9.867,
        0,
        2,
        13.133,
        0,
        2,
        13.333,
        0
      ]
    },
    {
      "Target": "Parameter",
      "Id": "ParamZS1",
      "FadeInTime": -1.0,
      "FadeOutTime": -1.0,
      "Segments": [
        0,
        0,
        2,
        0.233,
        0,
        0,
        0.267,
        30,
        2,
        6.667,
        30,
        2,
        10.167,
        30,
        0,
        10.2,
        0,
        2,
        13.133,
        0,
        2,
        13.333,
        0
      ]
    },
    {
      "Target": "Parameter",
      "Id": "ParamZS4",
      "FadeInTime": -1.0,
      "FadeOutTime": -1.0,
      "Segments": [
        0,
        0,
        2,
        0.233,
        0,
        0,
        0.267,
        30,
        2,
        4.3,
        30,
        0,
        4.333,
        0,
        2,
        7.067,
        0,
        0,
        7.1,
        30,
        2,
        10.167,
        30,
        0,
        10.2,
        0,
        2,
        13.133,
        0,
        2,
        13.333,
        0
      ]
    },
    {
      "Target": "Parameter",
      "Id": "ParamYS42",
      "FadeInTime": -1.0,
      "FadeOutTime": -1.0,
      "Segments": [
        0,
        0,
        2,
        4.3,
        0,
        0,
        4.333,
        30,
        2,
        7.067,
        30,
        0,
        7.1,
        0,
        2,
        13.333,
        0
      ]
    },
    {
      "Target": "Parameter",
      "Id": "ParamZ1",
      "FadeInTime": -1.0,
      "FadeOutTime": -1.0,
      "Segments": [
        0,
        -28,
        2,
        4.833,
        -28,
        2,
        6.667,
        -28,
        0,
        13.333,
        0
      ]
    },
    {
      "Target": "Parameter",
      "Id": "ParamBQLCX",
      "FadeInTime": -1.0,
      "FadeOutTime": -1.0,
      "Segments": [
        0,
        0,
        2,
        0.333,
        0,
        0,
        0.367,
        30,
        2,
        6.667,
        30,
        2,
        12.5,
        30,
        0,
        13.333,
        0
      ]
    },
    {
      "Target": "Parameter",
      "Id": "ParamBQLW",
      "FadeInTime": -1.0,
      "FadeOutTime": -1.0,
      "Segments": [
        0,
        0,
        2,
        5.5,
        0,
        0,
        5.733,
        30,
        2,
        9.3,
        30,
        0,
        13.333,
        0
      ]
    },
    {
      "Target": "Parameter",
      "Id": "ParamBQLXX",
      "FadeInTime": -1.0,
      "FadeOutTime": -1.0,
      "Segments": [
        0,
        0,
        2,
        5.567,
        0,
        0,
        5.6,
        30,
        0,
        5.7,
        0,
        0,
        5.833,
        30,
        0,
        6,
        0,
        2,
        6.1,
        0,
        0,
        6.2,
        30,
        2,
        6.267,
        30,
        0,
        6.333,
        0,
        2,
        13.333,
        0
      ]
    },
    {
      "Target": "Parameter",
      "Id": "ParamGSX",
      "FadeInTime": -1.0,
      "FadeOutTime": -1.0,
      "Segments": [
        0,
        0,
        0,
        1.233,
        11,
        0,
        2.867,
        0,
        0,
        5.167,
        4,
        0,
        6.667,
        0,
        2,
        7.9,
        0,
        2,
        9.533,
        0,
        0,
        11,
        -7,
        1,
        11.122,
        -7,
        11.245,
        -5.1,
        11.367,
        -2.177,
        1,
        11.689,
        5.528,
        12.011,
        9,
        12.333,
        9,
        0,
        13.333,
        0
      ]
    },
    {
      "Target": "Parameter",
      "Id": "ParamGSY",
      "FadeInTime": -1.0,
      "FadeOutTime": -1.0,
      "Segments": [
        0,
        0,
        0,
        1.233,
        6,
        1,
        1.778,
        6,
        2.322,
        1.384,
        2.867,
        0,
        1,
        3.634,
        -1.949,
        4.4,
        -2,
        5.167,
        -2,
        0,
        6.667,
        0,
        0,
        7.9,
        -1,
        1,
        8.444,
        -1,
        8.989,
        -1.174,
        9.533,
        0,
        1,
        10.022,
        1.054,
        10.511,
        11,
        11,
        11,
        1,
        11.444,
        11,
        11.889,
        8.113,
        12.333,
        4,
        1,
        12.666,
        0.915,
        13,
        0,
        13.333,
        0
      ]
    },
    {
      "Target": "Parameter",
      "Id": "ParamWJJ",
      "FadeInTime": -1.0,
      "FadeOutTime": -1.0,
      "Segments": [
        0,
        0,
        0,
        1.067,
        -25,
        0,
        2.767,
        22,
        0,
        3.333,
        0,
        2,
        6.667,
        0,
        0,
        7.733,
        -25,
        0,
        9.433,
        22,
        0,
        10,
        0,
        2,
        13.333,
        0
      ]
    },
    {
      "Target": "Parameter",
      "Id": "Paramty",
      "FadeInTime": -1.0,
      "FadeOutTime": -1.0,
      "Segments": [
        0,
        -30,
        0,
        0.8,
        16,
        0,
        3.333,
        -30,
        0,
        4.133,
        16,
        0,
        6.667,
        -30,
        0,
        7.467,
        16,
        0,
        10,
        -30,
        0,
        10.8,
        16,
        0,
        13.333,
        -30
      ]
    },
    {
      "Target": "Parameter",
      "Id": "ParamZY",
      "FadeInTime": -1.0,
      "FadeOutTime": -1.0,
      "Segments": [
        0,
        -30,
        2,
        2.067,
        -30,
        0,
        2.367,
        30,
        0,
        2.7,
        -30,
        2,
        3.333,
        -30,
        2,
        5.4,
        -30,
        0,
        5.7,
        30,
        0,
        6.033,
        -30,
        2,
        6.667,
        -30,
        2,
        8.733,
        -30,
        0,
        9.033,
        30,
        0,
        9.367,
        -30,
        2,
        10,
        -30,
        2,
        12.067,
        -30,
        0,
        12.367,
        30,
        0,
        12.7,
        -30,
        2,
        13.333,
        -30
      ]
    },
    {
      "Target": "Parameter",
      "Id": "ParamYBDXZ",
      "FadeInTime": -1.0,
      "FadeOutTime": -1.0,
      "Segments": [
        0,
        0,
        0,
        2,
        1.26,
        0,
        3.333,
        0,
        2,
        6.667,
        0,
        0,
        8.667,
        1.26,
        0,
        10,
        0,
        2,
        13.333,
        0
      ]
    },
    {
      "Target": "Parameter",
      "Id": "ParamYS",
      "FadeInTime": -1.0,
      "FadeOutTime": -1.0,
      "Segments": [
        0,
        0,
        0,
        1.467,
        -5,
        0,
        3.333,
        0,
        2,
        6.667,
        0,
        0,
        8.133,
        -5,
        0,
        10,
        0,
        2,
        13.333,
        0
      ]
    },
    {
      "Target": "Parameter",
      "Id": "ParamSTDC",
      "FadeInTime": -1.0,
      "FadeOutTime": -1.0,
      "Segments": [
        0,
        0,
        1,
        0.233,
        2.344,
        0.467,
        9.96,
        0.7,
        9.96,
        0,
        2.233,
        -3.98,
        1,
        2.6,
        -3.98,
        2.966,
        -3.684,
        3.333,
        0,
        1,
        3.566,
        2.344,
        3.8,
        9.96,
        4.033,
        9.96,
        0,
        5.567,
        -3.98,
        1,
        5.934,
        -3.98,
        6.3,
        -3.684,
        6.667,
        0,
        1,
        6.9,
        2.344,
        7.134,
        9.96,
        7.367,
        9.96,
        0,
        8.9,
        -3.98,
        1,
        9.267,
        -3.98,
        9.633,
        -3.684,
        10,
        0,
        1,
        10.233,
        2.344,
        10.467,
        9.96,
        10.7,
        9.96,
        0,
        12.233,
        -3.98,
        0,
        13.333,
        0
      ]
    },
    {
      "Target": "Parameter",
      "Id": "ParamSTDZY",
      "FadeInTime": -1.0,
      "FadeOutTime": -1.0,
      "Segments": [
        0,
        0,
        1,
        0.4,
        3.988,
        0.8,
        9.64,
        1.2,
        9.64,
        0,
        2.667,
        -2,
        1,
        2.889,
        -2,
        3.111,
        -2.216,
        3.333,
        0,
        1,
        3.733,
        3.988,
        4.133,
        9.64,
        4.533,
        9.64,
        0,
        6,
        -2,
        1,
        6.222,
        -2,
        6.445,
        -2.216,
        6.667,
        0,
        1,
        7.067,
        3.988,
        7.467,
        9.64,
        7.867,
        9.64,
        0,
        9.333,
        -2,
        1,
        9.555,
        -2,
        9.778,
        -2.216,
        10,
        0,
        1,
        10.4,
        3.988,
        10.8,
        9.64,
        11.2,
        9.64,
        0,
        12.667,
        -2,
        0,
        13.333,
        0
      ]
    },
    {
      "Target": "Parameter",
      "Id": "Paramqzy",
      "FadeInTime": -1.0,
      "FadeOutTime": -1.0,
      "Segments": [
        0,
        0,
        2,
        0.3,
        0,
        0,
        1.433,
        10,
        0,
        2.8,
        -10,
        0,
        3.333,
        0,
        2,
        3.633,
        0,
        0,
        4.767,
        10,
        0,
        6.133,
        -10,
        0,
        6.667,
        0,
        2,
        6.967,
        0,
        0,
        8.1,
        10,
        0,
        9.467,
        -10,
        0,
        10,
        0,
        2,
        10.3,
        0,
        0,
        11.433,
        10,
        0,
        12.8,
        -10,
        0,
        13.333,
        0
      ]
    },
    {
      "Target": "Parameter",
      "Id": "ParamQZx",
      "FadeInTime": -1.0,
      "FadeOutTime": -1.0,
      "Segments": [
        0,
        0,
        0,
        1.033,
        -12,
        0,
        1.767,
        0,
        0,
        2.667,
        -12,
        0,
        3.333,
        0,
        0,
        4.367,
        -12,
        0,
        5.1,
        0,
        0,
        6,
        -12,
        0,
        6.667,
        0,
        0,
        7.7,
        -12,
        0,
        8.433,
        0,
        0,
        9.333,
        -12,
        0,
        10,
        0,
        0,
        11.033,
        -12,
        0,
        11.767,
        0,
        0,
        12.667,
        -12,
        0,
        13.333,
        0
      ]
    },
    {
      "Target": "Parameter",
      "Id": "ParamYPY",
      "FadeInTime": -1.0,
      "FadeOutTime": -1.0,
      "Segments": [
        0,
        0,
        0,
        0.633,
        22,
        1,
        0.966,
        22,
        1.3,
        9.953,
        1.633,
        6.48,
        1,
        2.2,
        0.576,
        2.766,
        0,
        3.333,
        0,
        0,
        4.967,
        6.48,
        0,
        6.667,
        0,
        0,
        8.3,
        6.48,
        0,
        10,
        0,
        0,
        11.633,
        6.48,
        0,
        13.333,
        0
      ]
    },
    {
      "Target": "Parameter",
      "Id": "ParamBodyAngleZ",
      "FadeInTime": -1.0,
      "FadeOutTime": -1.0,
      "Segments": [
        0,
        0,
        0,
        0.7,
        2,
        0,
        1.633,
        -3,
        0,
        3.333,
        0,
        0,
        4.767,
        -2,
        1,
        5.4,
        -2,
        6.034,
        -0.827,
        6.667,
        0,
        1,
        7.211,
        0.711,
        7.756,
        0.74,
        8.3,
        0.74,
        0,
        10,
        0,
        0,
        10.767,
        3,
        0,
        12.1,
        -2,
        0,
        13.333,
        0
      ]
    },
    {
      "Target": "Parameter",
      "Id": "ParamBodyAngleX",
      "FadeInTime": -1.0,
      "FadeOutTime": -1.0,
      "Segments": [
        0,
        0,
        0,
        0.867,
        2,
        0,
        3.333,
        0,
        0,
        4.2,
        2,
        0,
        6.667,
        0,
        0,
        7.533,
        2,
        0,
        10,
        0,
        0,
        10.8,
        5,
        0,
        12.267,
        -3,
        0,
        13.333,
        0
      ]
    },
    {
      "Target": "Parameter",
      "Id": "ParamBodyAngleY",
      "FadeInTime": -1.0,
      "FadeOutTime": -1.0,
      "Segments": [
        0,
        0,
        0,
        0.8,
        -7,
        0,
        2.333,
        5,
        0,
        3.333,
        0,
        0,
        4.133,
        10,
        0,
        5.667,
        -3,
        0,
        6.467,
        10,
        2,
        7.467,
        10,
        0,
        9,
        -3,
        1,
        9.333,
        -3,
        9.667,
        -2.979,
        10,
        0,
        1,
        10.267,
        2.383,
        10.533,
        10,
        10.8,
        10,
        0,
        12.333,
        -3,
        0,
        13.333,
        0
      ]
    },
    {
      "Target": "Parameter",
      "Id": "ParamSTQQ",
      "FadeInTime": -1.0,
      "FadeOutTime": -1.0,
      "Segments": [
        0,
        0,
        0,
        0.633,
        15,
        1,
        0.922,
        15,
        1.211,
        2.027,
        1.5,
        1.74,
        1,
        2.289,
        0.956,
        3.078,
        0.796,
        3.867,
        0,
        1,
        4.178,
        -0.314,
        4.489,
        -10,
        4.8,
        -10,
        1,
        5.111,
        -10,
        5.422,
        -10.193,
        5.733,
        -7,
        1,
        5.978,
        -4.491,
        6.222,
        18,
        6.467,
        18,
        1,
        7.034,
        18,
        7.6,
        3.624,
        8.167,
        1.74,
        1,
        8.778,
        -0.292,
        9.389,
        0,
        10,
        0,
        0,
        11.5,
        1.74,
        0,
        13.333,
        0
      ]
    },
    {
      "Target": "Parameter",
      "Id": "ParamJB",
      "FadeInTime": -1.0,
      "FadeOutTime": -1.0,
      "Segments": [
        0,
        0,
        0,
        0.567,
        -30,
        0,
        1.8,
        14,
        0,
        3.333,
        -30,
        2,
        5.3,
        -30,
        0,
        6.3,
        30,
        0,
        8.467,
        -30,
        0,
        10,
        0,
        0,
        11.067,
        -30,
        0,
        12.467,
        11,
        0,
        13.333,
        0
      ]
    },
    {
      "Target": "Parameter",
      "Id": "ParamTBDZ",
      "FadeInTime": -1.0,
      "FadeOutTime": -1.0,
      "Segments": [
        0,
        0,
        0,
        1.433,
        8,
        0,
        2.833,
        -12,
        0,
        4.767,
        21,
        0,
        6.667,
        0,
        0,
        8.1,
        8,
        0,
        10,
        0,
        0,
        11.433,
        8,
        0,
        13.333,
        0
      ]
    },
    {
      "Target": "Parameter",
      "Id": "ParamBreath",
      "FadeInTime": -1.0,
      "FadeOutTime": -1.0,
      "Segments": [
        0,
        0,
        0,
        1.5,
        1,
        0,
        3.333,
        0,
        0,
        4.833,
        1,
        0,
        6.667,
        0,
        0,
        8.167,
        1,
        0,
        10,
        0,
        0,
        11.5,
        1,
        0,
        13.333,
        0
      ]
    },
    {
      "Target": "Parameter",
      "Id": "ParamAngleY",
      "FadeInTime": -1.0,
      "FadeOutTime": -1.0,
      "Segments": [
        0,
        0,
        0,
        1.6,
        30,
        0,
        3.333,
        0,
        0,
        4.933,
        30,
        0,
        6.033,
        -15,
        0,
        6.833,
        30,
        2,
        8.267,
        30,
        0,
        10,
        0,
        0,
        11.6,
        30,
        0,
        13.333,
        0
      ]
    },
    {
      "Target": "Parameter",
      "Id": "ParamAngleZ",
      "FadeInTime": -1.0,
      "FadeOutTime": -1.0,
      "Segments": [
        0,
        0,
        0,
        1.933,
        7,
        0,
        3.333,
        0,
        1,
        3.978,
        0,
        4.622,
        2.042,
        5.267,
        7,
        1,
        5.567,
        9.308,
        5.867,
        11,
        6.167,
        11,
        0,
        6.667,
        0,
        0,
        8.6,
        7,
        0,
        10,
        0,
        0,
        11.933,
        7,
        0,
        13.333,
        0
      ]
    },
    {
      "Target": "Parameter",
      "Id": "ParamEyeLOpen",
      "FadeInTime": -1.0,
      "FadeOutTime": -1.0,
      "Segments": [
        0,
        1,
        2,
        0.433,
        1,
        0,
        0.7,
        0,
        0,
        1.033,
        1,
        2,
        2.1,
        1,
        0,
        2.367,
        0,
        0,
        2.7,
        1,
        2,
        3.333,
        1,
        2,
        4.133,
        1,
        0,
        4.4,
        0,
        0,
        4.733,
        1,
        2,
        6.667,
        1,
        2,
        7.467,
        1,
        0,
        7.733,
        0,
        0,
        8.067,
        1,
        0,
        10.333,
        0,
        2,
        10.667,
        0,
        0,
        11.067,
        1,
        2,
        11.667,
        1,
        0,
        11.9,
        0,
        0,
        12.2,
        1,
        2,
        13.333,
        1
      ]
    },
    {
      "Target": "Parameter",
      "Id": "ParamEyeROpen",
      "FadeInTime": -1.0,
      "FadeOutTime": -1.0,
      "Segments": [
        0,
        1,
        2,
        0.433,
        1,
        0,
        0.7,
        0,
        0,
        1.033,
        1,
        2,
        2.1,
        1,
        0,
        2.367,
        0,
        0,
        2.7,
        1,
        2,
        3.333,
        1,
        2,
        4.133,
        1,
        0,
        4.4,
        0,
        0,
        4.733,
        1,
        2,
        6.667,
        1,
        2,
        7.467,
        1,
        0,
        7.733,
        0,
        0,
        8.067,
        1,
        0,
        10.333,
        0,
        2,
        10.667,
        0,
        0,
        11.067,
        1,
        2,
        11.667,
        1,
        0,
        11.9,
        0,
        0,
        12.2,
        1,
        2,
        13.333,
        1
      ]
    },
    {
      "Target": "Parameter",
      "Id": "ParamGGSD",
      "FadeInTime": -1.0,
      "FadeOutTime": -1.0,
      "Segments": [
        0,
        0,
        0,
        6.433,
        23,
        0,
        6.867,
        -14,
        0,
        7.333,
        20,
        0,
        7.9,
        -22,
        0,
        8.4,
        23,
        0,
        8.8,
        -14,
        0,
        9.2,
        20,
        0,
        9.7,
        -22,
        0,
        10.1,
        23,
        2,
        10.633,
        23,
        0,
        11.033,
        -14,
        0,
        11.4,
        20,
        0,
        11.9,
        -22,
        0,
        12.333,
        23,
        0,
        12.7,
        -14,
        0,
        13.1,
        20,
        1,
        13.178,
        20,
        13.255,
        13.965,
        13.333,
        0
      ]
    },
    {
      "Target": "Parameter",
      "Id": "ParamGG2DCX",
      "FadeInTime": -1.0,
      "FadeOutTime": -1.0,
      "Segments": [
        0,
        0,
        2,
        6.667,
        0,
        0,
        7.1,
        30,
        2,
        12.3,
        30,
        0,
        13.333,
        0
      ]
    },
    {
      "Target": "Parameter",
      "Id": "ParamYL",
      "FadeInTime": -1.0,
      "FadeOutTime": -1.0,
      "Segments": [
        0,
        0,
        2,
        6.667,
        0,
        0,
        10.867,
        30,
        0,
        13.333,
        0
      ]
    },
    {
      "Target": "Parameter",
      "Id": "ParamLB",
      "FadeInTime": -1.0,
      "FadeOutTime": -1.0,
      "Segments": [
        0,
        0,
        2,
        5.933,
        0,
        0,
        6.1,
        30,
        2,
        10.533,
        30,
        0,
        10.833,
        0,
        2,
        13.333,
        0
      ]
    },
    {
      "Target": "PartOpacity",
      "Id": "Part20",
      "FadeInTime": -1.0,
      "FadeOutTime": -1.0,
      "Segments": [
        0,
        1,
        2,
        6.67,
        1,
        2,
        13.33,
        1
      ]
    },
    {
      "Target": "PartOpacity",
      "Id": "Part29",
      "FadeInTime": -1.0,
      "FadeOutTime": -1.0,
      "Segments": [
        0,
        1,
        2,
        6.67,
        1,
        2,
        13.33,
        1
      ]
    },
    {
      "Target": "PartOpacity",
      "Id": "Part50",
      "FadeInTime": -1.0,
      "FadeOutTime": -1.0,
      "Segments": [
        0,
        1,
        2,
        6.67,
        1,
        2,
        13.33,
        1
      ]
    },
    {
      "Target": "PartOpacity",
      "Id": "Part19",
      "FadeInTime": -1.0,
      "FadeOutTime": -1.0,
      "Segments": [
        0,
        1,
        2,
        6.67,
        1,
        2,
        13.33,
        1
      ]
    },
    {
      "Target": "PartOpacity",
      "Id": "Part28",
      "FadeInTime": -1.0,
      "FadeOutTime": -1.0,
      "Segments": [
        0,
        1,
        2,
        6.67,
        1,
        2,
        13.33,
        1
      ]
    },
    {
      "Target": "PartOpacity",
      "Id": "Part31",
      "FadeInTime": -1.0,
      "FadeOutTime": -1.0,
      "Segments": [
        0,
        1,
        2,
        6.67,
        1,
        2,
        13.33,
        1
      ]
    },
    {
      "Target": "PartOpacity",
      "Id": "toubu2",
      "FadeInTime": -1.0,
      "FadeOutTime": -1.0,
      "Segments": [
        0,
        1,
        2,
        6.67,
        1,
        2,
        13.33,
        1
      ]
    },
    {
      "Target": "PartOpacity",
      "Id": "Part35",
      "FadeInTime": -1.0,
      "FadeOutTime": -1.0,
      "Segments": [
        0,
        1,
        2,
        6.67,
        1,
        2,
        13.33,
        1
      ]
    },
    {
      "Target": "PartOpacity",
      "Id": "Part39",
      "FadeInTime": -1.0,
      "FadeOutTime": -1.0,
      "Segments": [
        0,
        1,
        2,
        6.67,
        1,
        2,
        13.33,
        1
      ]
    },
    {
      "Target": "PartOpacity",
      "Id": "Part44",
      "FadeInTime": -1.0,
      "FadeOutTime": -1.0,
      "Segments": [
        0,
        1,
        2,
        6.67,
        1,
        2,
        13.33,
        1
      ]
    },
    {
      "Target": "PartOpacity",
      "Id": "Part45",
      "FadeInTime": -1.0,
      "FadeOutTime": -1.0,
      "Segments": [
        0,
        1,
        2,
        6.67,
        1,
        2,
        13.33,
        1
      ]
    },
    {
      "Target": "PartOpacity",
      "Id": "Part27",
      "FadeInTime": -1.0,
      "FadeOutTime": -1.0,
      "Segments": [
        0,
        1,
        2,
        6.67,
        1,
        2,
        13.33,
        1
      ]
    },
    {
      "Target": "PartOpacity",
      "Id": "Part40",
      "FadeInTime": -1.0,
      "FadeOutTime": -1.0,
      "Segments": [
        0,
        1,
        2,
        6.67,
        1,
        2,
        13.33,
        1
      ]
    },
    {
      "Target": "PartOpacity",
      "Id": "Part18",
      "FadeInTime": -1.0,
      "FadeOutTime": -1.0,
      "Segments": [
        0,
        1,
        2,
        6.67,
        1,
        2,
        13.33,
        1
      ]
    },
    {
      "Target": "PartOpacity",
      "Id": "Part23",
      "FadeInTime": -1.0,
      "FadeOutTime": -1.0,
      "Segments": [
        0,
        1,
        2,
        6.67,
        1,
        2,
        13.33,
        0
      ]
    },
    {
      "Target": "PartOpacity",
      "Id": "Part24",
      "FadeInTime": -1.0,
      "FadeOutTime": -1.0,
      "Segments": [
        0,
        1,
        2,
        6.67,
        1,
        2,
        13.33,
        1
      ]
    },
    {
      "Target": "PartOpacity",
      "Id": "Part25",
      "FadeInTime": -1.0,
      "FadeOutTime": -1.0,
      "Segments": [
        0,
        1,
        2,
        6.67,
        1,
        2,
        13.33,
        1
      ]
    },
    {
      "Target": "PartOpacity",
      "Id": "Part26",
      "FadeInTime": -1.0,
      "FadeOutTime": -1.0,
      "Segments": [
        0,
        1,
        2,
        6.67,
        1,
        2,
        13.33,
        1
      ]
    },
    {
      "Target": "PartOpacity",
      "Id": "Part",
      "FadeInTime": -1.0,
      "FadeOutTime": -1.0,
      "Segments": [
        0,
        1,
        2,
        6.67,
        1,
        2,
        13.33,
        1
      ]
    },
    {
      "Target": "PartOpacity",
      "Id": "Part34",
      "FadeInTime": -1.0,
      "FadeOutTime": -1.0,
      "Segments": [
        0,
        1,
        2,
        3.33,
        1,
        2,
        6.67,
        1,
        2,
        10,
        1,
        2,
        13.33,
        1
      ]
    },
    {
      "Target": "PartOpacity",
      "Id": "Part2",
      "FadeInTime": -1.0,
      "FadeOutTime": -1.0,
      "Segments": [
        0,
        1,
        2,
        3.33,
        1,
        2,
        6.67,
        1,
        2,
        10,
        1,
        2,
        13.33,
        1
      ]
    },
    {
      "Target": "PartOpacity",
      "Id": "Part3",
      "FadeInTime": -1.0,
      "FadeOutTime": -1.0,
      "Segments": [
        0,
        1,
        2,
        3.33,
        1,
        2,
        6.67,
        1,
        2,
        10,
        1,
        2,
        13.33,
        1
      ]
    },
    {
      "Target": "PartOpacity",
      "Id": "Part41",
      "FadeInTime": -1.0,
      "FadeOutTime": -1.0,
      "Segments": [
        0,
        1,
        2,
        6.67,
        1,
        2,
        13.33,
        1
      ]
    },
    {
      "Target": "PartOpacity",
      "Id": "Part42",
      "FadeInTime": -1.0,
      "FadeOutTime": -1.0,
      "Segments": [
        0,
        1,
        2,
        6.67,
        1,
        2,
        13.33,
        1
      ]
    },
    {
      "Target": "PartOpacity",
      "Id": "Part4",
      "FadeInTime": -1.0,
      "FadeOutTime": -1.0,
      "Segments": [
        0,
        1,
        2,
        3.33,
        1,
        2,
        6.67,
        1,
        2,
        10,
        1,
        2,
        13.33,
        1
      ]
    },
    {
      "Target": "PartOpacity",
      "Id": "toubu",
      "FadeInTime": -1.0,
      "FadeOutTime": -1.0,
      "Segments": [
        0,
        1,
        2,
        3.33,
        1,
        2,
        6.67,
        1,
        2,
        10,
        1,
        2,
        13.33,
        1
      ]
    },
    {
      "Target": "PartOpacity",
      "Id": "Part5",
      "FadeInTime": -1.0,
      "FadeOutTime": -1.0,
      "Segments": [
        0,
        1,
        2,
        3.33,
        1,
        2,
        6.67,
        1,
        2,
        10,
        1,
        2,
        13.33,
        1
      ]
    },
    {
      "Target": "PartOpacity",
      "Id": "Part6",
      "FadeInTime": -1.0,
      "FadeOutTime": -1.0,
      "Segments": [
        0,
        1,
        2,
        3.33,
        1,
        2,
        6.67,
        1,
        2,
        10,
        1,
        2,
        13.33,
        1
      ]
    },
    {
      "Target": "PartOpacity",
      "Id": "Part7",
      "FadeInTime": -1.0,
      "FadeOutTime": -1.0,
      "Segments": [
        0,
        1,
        2,
        3.33,
        1,
        2,
        6.67,
        1,
        2,
        10,
        1,
        2,
        13.33,
        1
      ]
    },
    {
      "Target": "PartOpacity",
      "Id": "youyan",
      "FadeInTime": -1.0,
      "FadeOutTime": -1.0,
      "Segments": [
        0,
        1,
        2,
        3.33,
        1,
        2,
        6.67,
        1,
        2,
        10,
        1,
        2,
        13.33,
        1
      ]
    },
    {
      "Target": "PartOpacity",
      "Id": "zuoyan",
      "FadeInTime": -1.0,
      "FadeOutTime": -1.0,
      "Segments": [
        0,
        1,
        2,
        3.33,
        1,
        2,
        6.67,
        1,
        2,
        10,
        1,
        2,
        13.33,
        1
      ]
    },
    {
      "Target": "PartOpacity",
      "Id": "Part8",
      "FadeInTime": -1.0,
      "FadeOutTime": -1.0,
      "Segments": [
        0,
        1,
        2,
        3.33,
        1,
        2,
        6.67,
        1,
        2,
        10,
        1,
        2,
        13.33,
        1
      ]
    },
    {
      "Target": "PartOpacity",
      "Id": "Part17",
      "FadeInTime": -1.0,
      "FadeOutTime": -1.0,
      "Segments": [
        0,
        1,
        2,
        3.33,
        1,
        2,
        6.67,
        1,
        2,
        10,
        1,
        2,
        13.33,
        1
      ]
    },
    {
      "Target": "PartOpacity",
      "Id": "Part16",
      "FadeInTime": -1.0,
      "FadeOutTime": -1.0,
      "Segments": [
        0,
        1,
        2,
        3.33,
        1,
        2,
        6.67,
        1,
        2,
        10,
        1,
        2,
        13.33,
        1
      ]
    },
    {
      "Target": "PartOpacity",
      "Id": "Part9",
      "FadeInTime": -1.0,
      "FadeOutTime": -1.0,
      "Segments": [
        0,
        1,
        2,
        3.33,
        1,
        2,
        6.67,
        1,
        2,
        10,
        1,
        2,
        13.33,
        1
      ]
    },
    {
      "Target": "PartOpacity",
      "Id": "Part10",
      "FadeInTime": -1.0,
      "FadeOutTime": -1.0,
      "Segments": [
        0,
        1,
        2,
        3.33,
        1,
        2,
        6.67,
        1,
        2,
        10,
        1,
        2,
        13.33,
        1
      ]
    },
    {
      "Target": "PartOpacity",
      "Id": "Part11",
      "FadeInTime": -1.0,
      "FadeOutTime": -1.0,
      "Segments": [
        0,
        1,
        2,
        3.33,
        1,
        2,
        6.67,
        1,
        2,
        10,
        1,
        2,
        13.33,
        1
      ]
    },
    {
      "Target": "PartOpacity",
      "Id": "Part12",
      "FadeInTime": -1.0,
      "FadeOutTime": -1.0,
      "Segments": [
        0,
        1,
        2,
        3.33,
        1,
        2,
        6.67,
        1,
        2,
        10,
        1,
        2,
        13.33,
        1
      ]
    },
    {
      "Target": "PartOpacity",
      "Id": "Part13",
      "FadeInTime": -1.0,
      "FadeOutTime": -1.0,
      "Segments": [
        0,
        1,
        2,
        3.33,
        1,
        2,
        6.67,
        1,
        2,
        10,
        1,
        2,
        13.33,
        1
      ]
    },
    {
      "Target": "PartOpacity",
      "Id": "Part14",
      "FadeInTime": -1.0,
      "FadeOutTime": -1.0,
      "Segments": [
        0,
        1,
        2,
        3.33,
        1,
        2,
        6.67,
        1,
        2,
        10,
        1,
        2,
        13.33,
        1
      ]
    },
    {
      "Target": "PartOpacity",
      "Id": "Part15",
      "FadeInTime": -1.0,
      "FadeOutTime": -1.0,
      "Segments": [
        0,
        1,
        2,
        3.33,
        1,
        2,
        6.67,
        1,
        2,
        10,
        1,
        2,
        13.33,
        1
      ]
    },
    {
      "Target": "PartOpacity",
      "Id": "dianpingche",
      "FadeInTime": -1.0,
      "FadeOutTime": -1.0,
      "Segments": [
        0,
        1,
        2,
        3.33,
        1,
        2,
        6.67,
        1,
        2,
        10,
        1,
        2,
        13.33,
        1
      ]
    },
    {
      "Target": "Model",
      "Id": "Opacity",
      "FadeInTime": -1.0,
      "FadeOutTime": -1.0,
      "Segments": [
        0,
        1,
        0,
        13.333,
        1
      ]
    },
    {
      "Target": "Parameter",
      "Id": "Param_EFFECT_SQUASH",
      "FadeInTime": -1.0,
      "FadeOutTime": -1.0,
      "Segments": [
        0,
        0,
        0,
        13.333,
        0
      ]
    },
    {
      "Target": "Parameter",
      "Id": "Param_EFFECT_MOVE_Y",
      "FadeInTime": -1.0,
      "FadeOutTime": -1.0,
      "Segments": [
        0,
        0,
        0,
        13.333,
        0
      ]
    },
    {
      "Target": "Parameter",
      "Id": "Param_EFFECT_HEART",
      "FadeInTime": -1.0,
      "FadeOutTime": -1.0,
      "Segments": [
        0,
        0,
        0,
        13.333,
        0
      ]
    },
    {
      "Target": "Parameter",
      "Id": "Param_EFFECT_FEEL",
      "FadeInTime": -1.0,
      "FadeOutTime": -1.0,
      "Segments": [
        0,
        0,
        0,
        13.333,
        0
      ]
    },
    {
      "Target": "Parameter",
      "Id": "Param_EFFECT_STAR",
      "FadeInTime": -1.0,
      "FadeOutTime": -1.0,
      "Segments": [
        0,
        0,
        0,
        13.333,
        0
      ]
    },
    {
      "Target": "Parameter",
      "Id": "ParamQH",
      "FadeInTime": -1.0,
      "FadeOutTime": -1.0,
      "Segments": [
        0,
        0,
        0,
        13.333,
        0
      ]
    },
    {
      "Target": "Parameter",
      "Id": "ParamQBYC",
      "FadeInTime": -1.0,
      "FadeOutTime": -1.0,
      "Segments": [
        0,
        0,
        0,
        13.333,
        0
      ]
    },
    {
      "Target": "Parameter",
      "Id": "ParamBJDXDX",
      "FadeInTime": -1.0,
      "FadeOutTime": -1.0,
      "Segments": [
        0,
        0,
        0,
        13.333,
        0
      ]
    },
    {
      "Target": "Parameter",
      "Id": "ParamBJDXDY",
      "FadeInTime": -1.0,
      "FadeOutTime": -1.0,
      "Segments": [
        0,
        0,
        0,
        13.333,
        0
      ]
    },
    {
      "Target": "Parameter",
      "Id": "ParamBJDXDXZ",
      "FadeInTime": -1.0,
      "FadeOutTime": -1.0,
      "Segments": [
        0,
        0,
        0,
        13.333,
        0
      ]
    },
    {
      "Target": "Parameter",
      "Id": "ParamHCX",
      "FadeInTime": -1.0,
      "FadeOutTime": -1.0,
      "Segments": [
        0,
        0,
        0,
        13.333,
        0
      ]
    },
    {
      "Target": "Parameter",
      "Id": "ParamHSDKS",
      "FadeInTime": -1.0,
      "FadeOutTime": -1.0,
      "Segments": [
        0,
        0,
        0,
        13.333,
        0
      ]
    },
    {
      "Target": "Parameter",
      "Id": "ParamHSJTDQJ",
      "FadeInTime": -1.0,
      "FadeOutTime": -1.0,
      "Segments": [
        0,
        0,
        0,
        13.333,
        0
      ]
    },
    {
      "Target": "Parameter",
      "Id": "ParamLSJCX",
      "FadeInTime": -1.0,
      "FadeOutTime": -1.0,
      "Segments": [
        0,
        0,
        0,
        13.333,
        0
      ]
    },
    {
      "Target": "Parameter",
      "Id": "ParamLSSJKS",
      "FadeInTime": -1.0,
      "FadeOutTime": -1.0,
      "Segments": [
        0,
        0,
        0,
        13.333,
        0
      ]
    },
    {
      "Target": "Parameter",
      "Id": "Paramlsjy",
      "FadeInTime": -1.0,
      "FadeOutTime": -1.0,
      "Segments": [
        0,
        0,
        0,
        13.333,
        0
      ]
    },
    {
      "Target": "Parameter",
      "Id": "ParamBXQDCX",
      "FadeInTime": -1.0,
      "FadeOutTime": -1.0,
      "Segments": [
        0,
        0,
        0,
        13.333,
        0
      ]
    },
    {
      "Target": "Parameter",
      "Id": "ParamHQDCX",
      "FadeInTime": -1.0,
      "FadeOutTime": -1.0,
      "Segments": [
        0,
        0,
        0,
        13.333,
        0
      ]
    },
    {
      "Target": "Parameter",
      "Id": "ParamBSXSJ",
      "FadeInTime": -1.0,
      "FadeOutTime": -1.0,
      "Segments": [
        0,
        0,
        0,
        13.333,
        0
      ]
    },
    {
      "Target": "Parameter",
      "Id": "ParamZMCX",
      "FadeInTime": -1.0,
      "FadeOutTime": -1.0,
      "Segments": [
        0,
        0,
        0,
        13.333,
        0
      ]
    },
    {
      "Target": "Parameter",
      "Id": "ParamZMXZ",
      "FadeInTime": -1.0,
      "FadeOutTime": -1.0,
      "Segments": [
        0,
        0,
        0,
        13.333,
        0
      ]
    },
    {
      "Target": "Parameter",
      "Id": "Paramzks",
      "FadeInTime": -1.0,
      "FadeOutTime": -1.0,
      "Segments": [
        0,
        0,
        0,
        13.333,
        0
      ]
    },
    {
      "Target": "Parameter",
      "Id": "ParamZX",
      "FadeInTime": -1.0,
      "FadeOutTime": -1.0,
      "Segments": [
        0,
        0,
        0,
        13.333,
        0
      ]
    },
    {
      "Target": "Parameter",
      "Id": "ParamZDY",
      "FadeInTime": -1.0,
      "FadeOutTime": -1.0,
      "Segments": [
        0,
        0,
        0,
        13.333,
        0
      ]
    },
    {
      "Target": "Parameter",
      "Id": "ParamCDCX",
      "FadeInTime": -1.0,
      "FadeOutTime": -1.0,
      "Segments": [
        0,
        0,
        0,
        13.333,
        0
      ]
    },
    {
      "Target": "Parameter",
      "Id": "ParamZTDCX",
      "FadeInTime": -1.0,
      "FadeOutTime": -1.0,
      "Segments": [
        0,
        0,
        0,
        13.333,
        0
      ]
    },
    {
      "Target": "Parameter",
      "Id": "ParamZTDX",
      "FadeInTime": -1.0,
      "FadeOutTime": -1.0,
      "Segments": [
        0,
        0,
        0,
        13.333,
        0
      ]
    },
    {
      "Target": "Parameter",
      "Id": "ParamZTDY",
      "FadeInTime": -1.0,
      "FadeOutTime": -1.0,
      "Segments": [
        0,
        0,
        0,
        13.333,
        0
      ]
    },
    {
      "Target": "Parameter",
      "Id": "ParamZTDZ",
      "FadeInTime": -1.0,
      "FadeOutTime": -1.0,
      "Segments": [
        0,
        0,
        0,
        13.333,
        0
      ]
    },
    {
      "Target": "Parameter",
      "Id": "ParamZTKS",
      "FadeInTime": -1.0,
      "FadeOutTime": -1.0,
      "Segments": [
        0,
        0,
        0,
        13.333,
        0
      ]
    },
    {
      "Target": "Parameter",
      "Id": "ParamZTX",
      "FadeInTime": -1.0,
      "FadeOutTime": -1.0,
      "Segments": [
        0,
        0,
        0,
        13.333,
        0
      ]
    },
    {
      "Target": "Parameter",
      "Id": "ParamZTY",
      "FadeInTime": -1.0,
      "FadeOutTime": -1.0,
      "Segments": [
        0,
        0,
        0,
        13.333,
        0
      ]
    },
    {
      "Target": "Parameter",
      "Id": "ParamYLX",
      "FadeInTime": -1.0,
      "FadeOutTime": -1.0,
      "Segments": [
        0,
        0,
        0,
        13.333,
        0
      ]
    },
    {
      "Target": "Parameter",
      "Id": "ParamYLY",
      "FadeInTime": -1.0,
      "FadeOutTime": -1.0,
      "Segments": [
        0,
        0,
        0,
        13.333,
        0
      ]
    },
    {
      "Target": "Parameter",
      "Id": "ParamYLKS",
      "FadeInTime": -1.0,
      "FadeOutTime": -1.0,
      "Segments": [
        0,
        0,
        0,
        13.333,
        0
      ]
    },
    {
      "Target": "Parameter",
      "Id": "ParamYLCX",
      "FadeInTime": -1.0,
      "FadeOutTime": -1.0,
      "Segments": [
        0,
        0,
        0,
        13.333,
        0
      ]
    },
    {
      "Target": "Parameter",
      "Id": "ParamYLXZ",
      "FadeInTime": -1.0,
      "FadeOutTime": -1.0,
      "Segments": [
        0,
        0,
        0,
        13.333,
        0
      ]
    },
    {
      "Target": "Parameter",
      "Id": "ParamSX",
      "FadeInTime": -1.0,
      "FadeOutTime": -1.0,
      "Segments": [
        0,
        0,
        0,
        13.333,
        0
      ]
    },
    {
      "Target": "Parameter",
      "Id": "ParamSHKG",
      "FadeInTime": -1.0,
      "FadeOutTime": -1.0,
      "Segments": [
        0,
        0,
        0,
        13.333,
        0
      ]
    },
    {
      "Target": "Parameter",
      "Id": "ParamSHPS",
      "FadeInTime": -1.0,
      "FadeOutTime": -1.0,
      "Segments": [
        0,
        0,
        0,
        13.333,
        0
      ]
    },
    {
      "Target": "Parameter",
      "Id": "ParamPWCX",
      "FadeInTime": -1.0,
      "FadeOutTime": -1.0,
      "Segments": [
        0,
        0,
        0,
        13.333,
        0
      ]
    },
    {
      "Target": "Parameter",
      "Id": "ParamPWKS",
      "FadeInTime": -1.0,
      "FadeOutTime": -1.0,
      "Segments": [
        0,
        -30,
        0,
        13.333,
        -30
      ]
    },
    {
      "Target": "Parameter",
      "Id": "ParamZS2",
      "FadeInTime": -1.0,
      "FadeOutTime": -1.0,
      "Segments": [
        0,
        0,
        0,
        13.333,
        0
      ]
    },
    {
      "Target": "Parameter",
      "Id": "ParamYS2DB",
      "FadeInTime": -1.0,
      "FadeOutTime": -1.0,
      "Segments": [
        0,
        0,
        0,
        13.333,
        0
      ]
    },
    {
      "Target": "Parameter",
      "Id": "ParamZS3",
      "FadeInTime": -1.0,
      "FadeOutTime": -1.0,
      "Segments": [
        0,
        0,
        0,
        13.333,
        0
      ]
    },
    {
      "Target": "Parameter",
      "Id": "ParamZ2",
      "FadeInTime": -1.0,
      "FadeOutTime": -1.0,
      "Segments": [
        0,
        0,
        0,
        13.333,
        0
      ]
    },
    {
      "Target": "Parameter",
      "Id": "ParamZ2YS",
      "FadeInTime": -1.0,
      "FadeOutTime": -1.0,
      "Segments": [
        0,
        0,
        0,
        13.333,
        0
      ]
    },
    {
      "Target": "Parameter",
      "Id": "ParamZ3",
      "FadeInTime": -1.0,
      "FadeOutTime": -1.0,
      "Segments": [
        0,
        0,
        0,
        13.333,
        0
      ]
    },
    {
      "Target": "Parameter",
      "Id": "ParamZ4",
      "FadeInTime": -1.0,
      "FadeOutTime": -1.0,
      "Segments": [
        0,
        0,
        0,
        13.333,
        0
      ]
    },
    {
      "Target": "Parameter",
      "Id": "ParamZ5",
      "FadeInTime": -1.0,
      "FadeOutTime": -1.0,
      "Segments": [
        0,
        0,
        0,
        13.333,
        0
      ]
    },
    {
      "Target": "Parameter",
      "Id": "ParamJZ",
      "FadeInTime": -1.0,
      "FadeOutTime": -1.0,
      "Segments": [
        0,
        0,
        0,
        13.333,
        0
      ]
    },
    {
      "Target": "Parameter",
      "Id": "ParamJZGCX",
      "FadeInTime": -1.0,
      "FadeOutTime": -1.0,
      "Segments": [
        0,
        0,
        0,
        13.333,
        0
      ]
    },
    {
      "Target": "Parameter",
      "Id": "ParamJZGXZ",
      "FadeInTime": -1.0,
      "FadeOutTime": -1.0,
      "Segments": [
        0,
        0,
        0,
        13.333,
        0
      ]
    },
    {
      "Target": "Parameter",
      "Id": "ParamJZGKS",
      "FadeInTime": -1.0,
      "FadeOutTime": -1.0,
      "Segments": [
        0,
        0,
        0,
        13.333,
        0
      ]
    },
    {
      "Target": "Parameter",
      "Id": "ParamYD",
      "FadeInTime": -1.0,
      "FadeOutTime": -1.0,
      "Segments": [
        0,
        0,
        0,
        13.333,
        0
      ]
    },
    {
      "Target": "Parameter",
      "Id": "ParamZDT",
      "FadeInTime": -1.0,
      "FadeOutTime": -1.0,
      "Segments": [
        0,
        0,
        0,
        13.333,
        0
      ]
    },
    {
      "Target": "Parameter",
      "Id": "ParamZTT",
      "FadeInTime": -1.0,
      "FadeOutTime": -1.0,
      "Segments": [
        0,
        0,
        0,
        13.333,
        0
      ]
    },
    {
      "Target": "Parameter",
      "Id": "ParamZJ",
      "FadeInTime": -1.0,
      "FadeOutTime": -1.0,
      "Segments": [
        0,
        0,
        0,
        13.333,
        0
      ]
    },
    {
      "Target": "Parameter",
      "Id": "ParamQS",
      "FadeInTime": -1.0,
      "FadeOutTime": -1.0,
      "Segments": [
        0,
        0,
        0,
        13.333,
        0
      ]
    },
    {
      "Target": "Parameter",
      "Id": "ParamTS",
      "FadeInTime": -1.0,
      "FadeOutTime": -1.0,
      "Segments": [
        0,
        -30,
        0,
        13.333,
        -30
      ]
    },
    {
      "Target": "Parameter",
      "Id": "Paramze",
      "FadeInTime": -1.0,
      "FadeOutTime": -1.0,
      "Segments": [
        0,
        0,
        0,
        13.333,
        0
      ]
    },
    {
      "Target": "Parameter",
      "Id": "ParamYE",
      "FadeInTime": -1.0,
      "FadeOutTime": -1.0,
      "Segments": [
        0,
        0,
        0,
        13.333,
        0
      ]
    },
    {
      "Target": "Parameter",
      "Id": "ParamYQBXZ",
      "FadeInTime": -1.0,
      "FadeOutTime": -1.0,
      "Segments": [
        0,
        0,
        0,
        13.333,
        0
      ]
    },
    {
      "Target": "Parameter",
      "Id": "ParamSTDDQH",
      "FadeInTime": -1.0,
      "FadeOutTime": -1.0,
      "Segments": [
        0,
        -30,
        0,
        13.333,
        -30
      ]
    },
    {
      "Target": "Parameter",
      "Id": "ParamHairFront",
      "FadeInTime": -1.0,
      "FadeOutTime": -1.0,
      "Segments": [
        0,
        0,
        0,
        13.333,
        0
      ]
    },
    {
      "Target": "Parameter",
      "Id": "ParamTFBDQ2",
      "FadeInTime": -1.0,
      "FadeOutTime": -1.0,
      "Segments": [
        0,
        0,
        0,
        13.333,
        0
      ]
    },
    {
      "Target": "Parameter",
      "Id": "ParamQFWL",
      "FadeInTime": -1.0,
      "FadeOutTime": -1.0,
      "Segments": [
        0,
        0,
        0,
        13.333,
        0
      ]
    },
    {
      "Target": "Parameter",
      "Id": "ParamHairSide",
      "FadeInTime": -1.0,
      "FadeOutTime": -1.0,
      "Segments": [
        0,
        0,
        0,
        13.333,
        0
      ]
    },
    {
      "Target": "Parameter",
      "Id": "ParamDM",
      "FadeInTime": -1.0,
      "FadeOutTime": -1.0,
      "Segments": [
        0,
        0,
        0,
        13.333,
        0
      ]
    },
    {
      "Target": "Parameter",
      "Id": "ParamDMWL",
      "FadeInTime": -1.0,
      "FadeOutTime": -1.0,
      "Segments": [
        0,
        0,
        0,
        13.333,
        0
      ]
    },
    {
      "Target": "Parameter",
      "Id": "ParamWDYD",
      "FadeInTime": -1.0,
      "FadeOutTime": -1.0,
      "Segments": [
        0,
        0,
        0,
        13.333,
        0
      ]
    },
    {
      "Target": "Parameter",
      "Id": "ParamBAODAI",
      "FadeInTime": -1.0,
      "FadeOutTime": -1.0,
      "Segments": [
        0,
        0,
        0,
        13.333,
        0
      ]
    },
    {
      "Target": "Parameter",
      "Id": "ParamBDWL",
      "FadeInTime": -1.0,
      "FadeOutTime": -1.0,
      "Segments": [
        0,
        0,
        0,
        13.333,
        0
      ]
    },
    {
      "Target": "Parameter",
      "Id": "ParamEF",
      "FadeInTime": -1.0,
      "FadeOutTime": -1.0,
      "Segments": [
        0,
        0,
        0,
        13.333,
        0
      ]
    },
    {
      "Target": "Parameter",
      "Id": "ParamEFWL",
      "FadeInTime": -1.0,
      "FadeOutTime": -1.0,
      "Segments": [
        0,
        0,
        0,
        13.333,
        0
      ]
    },
    {
      "Target": "Parameter",
      "Id": "ParamFD",
      "FadeInTime": -1.0,
      "FadeOutTime": -1.0,
      "Segments": [
        0,
        0,
        0,
        13.333,
        0
      ]
    },
    {
      "Target": "Parameter",
      "Id": "ParamFDWL",
      "FadeInTime": -1.0,
      "FadeOutTime": -1.0,
      "Segments": [
        0,
        0,
        0,
        13.333,
        0
      ]
    },
    {
      "Target": "Parameter",
      "Id": "ParamHairBack",
      "FadeInTime": -1.0,
      "FadeOutTime": -1.0,
      "Segments": [
        0,
        0,
        0,
        13.333,
        0
      ]
    },
    {
      "Target": "Parameter",
      "Id": "ParamTBDX",
      "FadeInTime": -1.0,
      "FadeOutTime": -1.0,
      "Segments": [
        0,
        0,
        0,
        13.333,
        0
      ]
    },
    {
      "Target": "Parameter",
      "Id": "ParamTBDY",
      "FadeInTime": -1.0,
      "FadeOutTime": -1.0,
      "Segments": [
        0,
        0,
        0,
        13.333,
        0
      ]
    },
    {
      "Target": "Parameter",
      "Id": "ParamAngleX",
      "FadeInTime": -1.0,
      "FadeOutTime": -1.0,
      "Segments": [
        0,
        0,
        0,
        13.333,
        0
      ]
    },
    {
      "Target": "Parameter",
      "Id": "ParamJDR",
      "FadeInTime": -1.0,
      "FadeOutTime": -1.0,
      "Segments": [
        0,
        -30,
        0,
        13.333,
        -30
      ]
    },
    {
      "Target": "Parameter",
      "Id": "ParamYJSX",
      "FadeInTime": -1.0,
      "FadeOutTime": -1.0,
      "Segments": [
        0,
        30,
        0,
        13.333,
        30
      ]
    },
    {
      "Target": "Parameter",
      "Id": "ParamEyeSmile",
      "FadeInTime": -1.0,
      "FadeOutTime": -1.0,
      "Segments": [
        0,
        0,
        0,
        13.333,
        0
      ]
    },
    {
      "Target": "Parameter",
      "Id": "ParamEyeBallX",
      "FadeInTime": -1.0,
      "FadeOutTime": -1.0,
      "Segments": [
        0,
        0,
        0,
        13.333,
        0
      ]
    },
    {
      "Target": "Parameter",
      "Id": "ParamEyeBallY",
      "FadeInTime": -1.0,
      "FadeOutTime": -1.0,
      "Segments": [
        0,
        0,
        0,
        13.333,
        0
      ]
    },
    {
      "Target": "Parameter",
      "Id": "ParamYZKS",
      "FadeInTime": -1.0,
      "FadeOutTime": -1.0,
      "Segments": [
        0,
        0,
        0,
        13.333,
        0
      ]
    },
    {
      "Target": "Parameter",
      "Id": "ParamTKKS",
      "FadeInTime": -1.0,
      "FadeOutTime": -1.0,
      "Segments": [
        0,
        0,
        0,
        13.333,
        0
      ]
    },
    {
      "Target": "Parameter",
      "Id": "ParamBrowRY",
      "FadeInTime": -1.0,
      "FadeOutTime": -1.0,
      "Segments": [
        0,
        0,
        0,
        13.333,
        0
      ]
    },
    {
      "Target": "Parameter",
      "Id": "ParamBrowRX",
      "FadeInTime": -1.0,
      "FadeOutTime": -1.0,
      "Segments": [
        0,
        0,
        0,
        13.333,
        0
      ]
    },
    {
      "Target": "Parameter",
      "Id": "ParamBrowRAngle",
      "FadeInTime": -1.0,
      "FadeOutTime": -1.0,
      "Segments": [
        0,
        0,
        0,
        13.333,
        0
      ]
    },
    {
      "Target": "Parameter",
      "Id": "ParamBrowRForm",
      "FadeInTime": -1.0,
      "FadeOutTime": -1.0,
      "Segments": [
        0,
        0,
        0,
        13.333,
        0
      ]
    },
    {
      "Target": "Parameter",
      "Id": "ParamKZ",
      "FadeInTime": -1.0,
      "FadeOutTime": -1.0,
      "Segments": [
        0,
        30,
        0,
        13.333,
        30
      ]
    },
    {
      "Target": "Parameter",
      "Id": "ParamKZ1",
      "FadeInTime": -1.0,
      "FadeOutTime": -1.0,
      "Segments": [
        0,
        0,
        0,
        13.333,
        0
      ]
    },
    {
      "Target": "Parameter",
      "Id": "ParamKZ12",
      "FadeInTime": -1.0,
      "FadeOutTime": -1.0,
      "Segments": [
        0,
        30,
        0,
        13.333,
        30
      ]
    },
    {
      "Target": "Parameter",
      "Id": "ParamKZ2",
      "FadeInTime": -1.0,
      "FadeOutTime": -1.0,
      "Segments": [
        0,
        0,
        0,
        13.333,
        0
      ]
    },
    {
      "Target": "Parameter",
      "Id": "ParamKZ3",
      "FadeInTime": -1.0,
      "FadeOutTime": -1.0,
      "Segments": [
        0,
        0,
        0,
        13.333,
        0
      ]
    },
    {
      "Target": "Parameter",
      "Id": "ParamSQCX",
      "FadeInTime": -1.0,
      "FadeOutTime": -1.0,
      "Segments": [
        0,
        0,
        0,
        13.333,
        0
      ]
    },
    {
      "Target": "Parameter",
      "Id": "ParamSQX",
      "FadeInTime": -1.0,
      "FadeOutTime": -1.0,
      "Segments": [
        0,
        0,
        0,
        13.333,
        0
      ]
    },
    {
      "Target": "Parameter",
      "Id": "ParamSQY",
      "FadeInTime": -1.0,
      "FadeOutTime": -1.0,
      "Segments": [
        0,
        0,
        0,
        13.333,
        0
      ]
    },
    {
      "Target": "Parameter",
      "Id": "ParamMouthForm",
      "FadeInTime": -1.0,
      "FadeOutTime": -1.0,
      "Segments": [
        0,
        0,
        0,
        13.333,
        0
      ]
    },
    {
      "Target": "Parameter",
      "Id": "ParamZ11",
      "FadeInTime": -1.0,
      "FadeOutTime": -1.0,
      "Segments": [
        0,
        0,
        0,
        13.333,
        0
      ]
    },
    {
      "Target": "Parameter",
      "Id": "ParamZ22",
      "FadeInTime": -1.0,
      "FadeOutTime": -1.0,
      "Segments": [
        0,
        0,
        0,
        13.333,
        0
      ]
    },
    {
      "Target": "Parameter",
      "Id": "ParamMouthOpenY",
      "FadeInTime": -1.0,
      "FadeOutTime": -1.0,
      "Segments": [
        0,
        0,
        0,
        13.333,
        0
      ]
    },
    {
      "Target": "Parameter",
      "Id": "shetoutuchu",
      "FadeInTime": -1.0,
      "FadeOutTime": -1.0,
      "Segments": [
        0,
        0,
        0,
        13.333,
        0
      ]
    },
    {
      "Target": "Parameter",
      "Id": "shetouyaobai",
      "FadeInTime": -1.0,
      "FadeOutTime": -1.0,
      "Segments": [
        0,
        0,
        0,
        13.333,
        0
      ]
    },
    {
      "Target": "Parameter",
      "Id": "ParamSTBQL",
      "FadeInTime": -1.0,
      "FadeOutTime": -1.0,
      "Segments": [
        0,
        0,
        0,
        13.333,
        0
      ]
    },
    {
      "Target": "Parameter",
      "Id": "ParamCheek",
      "FadeInTime": -1.0,
      "FadeOutTime": -1.0,
      "Segments": [
        0,
        0,
        0,
        13.333,
        0
      ]
    },
    {
      "Target": "PartOpacity",
      "Id": "Part21",
      "FadeInTime": -1.0,
      "FadeOutTime": -1.0,
      "Segments": [
        0,
        1,
        0,
        13.333,
        1
      ]
    }
  ],
  "UserData": [
    {
      "Time": 0.0,
      "Value": ""
    },
    {
      "Time": 12.833,
      "Value": ""
    }
  ]
}